anchorax/__init__.py
anchorax/backprop.py
anchorax/regularization.py
anchorax/solvers.py
anchorax-0.1.0.dist-info/licenses/LICENSE
anchorax-0.1.0.dist-info/METADATA
anchorax-0.1.0.dist-info/WHEEL
anchorax-0.1.0.dist-info/top_level.txt
anchorax-0.1.0.dist-info/RECORD
