Metadata-Version: 2.4
Name: anchorax
Version: 0.1.0
Summary: Fixed-point solvers and differentiation utilities for implicit neural networks in JAX/Equinox.
Classifier: Development Status :: 4 - Beta
Classifier: Intended Audience :: Developers
Classifier: Intended Audience :: Science/Research
Classifier: Topic :: Scientific/Engineering :: Artificial Intelligence
Classifier: Programming Language :: Python :: 3.11
Classifier: Programming Language :: Python :: 3.12
Classifier: Programming Language :: Python :: 3.13
Classifier: Programming Language :: Python :: 3.14
Requires-Python: >=3.11
License-File: LICENSE
Requires-Dist: einops>=0.8.1
Requires-Dist: equinox>=0.12.1
Requires-Dist: jax>=0.6.0
Requires-Dist: jaxlib>=0.6.0
Dynamic: license-file
